MagicGoogle/__init__.py
MagicGoogle/config.py
MagicGoogle/magic_google.py
MagicGoogle/data/all_domain.txt
MagicGoogle/data/user_agents.txt
MagicGoogle-0.2.7.dist-info/DESCRIPTION.rst
MagicGoogle-0.2.7.dist-info/METADATA
MagicGoogle-0.2.7.dist-info/RECORD
MagicGoogle-0.2.7.dist-info/WHEEL
MagicGoogle-0.2.7.dist-info/metadata.json
MagicGoogle-0.2.7.dist-info/top_level.txt
